{"name":"Mikan, George","topVideo":"https://youtube.com/watch?v=LHcpuSRQ2vc","relatedLinks":[{"title":"George Mikan Stats | Basketball-Reference.com","url":"https://www.basketball-reference.com/players/m/mikange01.html"},{"title":"George Mikan - Wikipedia","url":"https://en.m.wikipedia.org/wiki/George_Mikan"},{"title":"Legends profile: George Mikan | NBA.com","url":"https://www.nba.com/news/history-nba-legend-george-mikan?amp=1"},{"title":"George Mikan - The Naismith Memorial Basketball Hall of Fame","url":"https://www.hoophall.com/hall-of-famers/george-mikan/"},{"title":"George Mikan | American basketball player | Britannica","url":"https://www.britannica.com/biography/George-Mikan"},{"title":"George Mikan [2021 Update]: Net Worth, Death, NBA & College","url":"https://playersbio.com/george-mikan/"},{"title":"George Mikan Stats, News, Bio | ESPN","url":"https://www.espn.com/nba/player/_/id/4147/george-mikan"},{"title":"George Mikan - NBA player profile page from WhatifSports","url":"https://www.whatifsports.com/nba-l/profile_player.asp?pid=1939"}],"bio":{"title":"George Mikan","description":"George Lawrence Mikan Jr., nicknamed \"Mr. Basketball\", was an American professional basketball player for the Chicago American Gears of the National Basketball League and the Minneapolis Lakers of the NBL, the Basketball Association of America and the National Basketball Association.","url":"https://en.m.wikipedia.org/wiki/George_Mikan","born":"June 18, 1924, Joliet, IL","died":"June 1, 2005, Scottsdale, AZ","height":"6′ 10″","spouse":"Patricia Lu Deveny (m. 1947–2005)","children":"Larry Mikan","education":"DePaul University (1942–1946), Archbishop Quigley Preparatory Seminary,  More","parents":"Minnie Mikan, Joseph Mikan","type":"American professional basketball player","images":[{"url":"https://encrypted-tbn0.gstatic.com/images?q=tbn:ANd9GcSREpoGofMtzzVQDRV_ij5Ei4KxT3svIdOIQA&s","source":"https://www.nba.com/news/history-nba-legend-george-mikan"},{"url":"https://encrypted-tbn0.gstatic.com/images?q=tbn:ANd9GcTJdfwZGEU-id6Z4r9xX1sPOVc7kZUAqZfaFg&s","source":"https://www.gettyimages.com/photos/george-mikan"},{"url":"https://encrypted-tbn0.gstatic.com/images?q=tbn:ANd9GcS95n0Sb4g3U6XTYkmnCcLU8ef5aeUKGEWmCA&s","source":"https://probasketballencyclopedia.com/player/george-mikan/"},{"url":"https://encrypted-tbn0.gstatic.com/images?q=tbn:ANd9GcTjiTE7K8BMcChWPFUDEsW0cq97Z3usb2bBXA&s","source":"https://playersbio.com/george-mikan/"},{"url":"https://encrypted-tbn0.gstatic.com/images?q=tbn:ANd9GcT7l0W0dwJhEbXSaVSY7xBVD2vEYPhneUjEng&s","source":"https://www.youtube.com/watch?v=FiH9ed48e2U"},{"url":"https://encrypted-tbn0.gstatic.com/images?q=tbn:ANd9GcQ4SlU4SFcreTLlqz_1gv6xgG3IoR4tc0fOEQ&s","source":"https://www.amazon.com/Mr-Basketball-George-Minneapolis-Lakers/dp/0816656754"},{"url":"https://encrypted-tbn0.gstatic.com/images?q=tbn:ANd9GcRdm3IZJekTpXFSr0NBG1xl-13lqrXkCFWncw&s","source":"https://en.wikipedia.org/wiki/George_Mikan"},{"url":"https://encrypted-tbn0.gstatic.com/images?q=tbn:ANd9GcQeY7wPeD2wYAVWHz1x2CRLs8PjyaCu58w0Ug&s","source":"https://lakersuk.com/2020/04/27/the-greatest-lakers-of-all-time-george-mikan/"}]},"stats":{"honors":[{"label":"Awards","results":[{"honor":"1953 All-Star Game Most Valuable Player","rank":"1953 All-Star Game Most Valuable Player"}]},{"label":"All-Star Games","results":[{"honor":"1951 NBA","rank":"1951 NBA"},{"honor":"1952 NBA","rank":"1952 NBA"},{"honor":"1953 NBA","rank":"1953 NBA"},{"honor":"1954 NBA","rank":"1954 NBA"}]},{"label":"Championships","results":[{"honor":"1949","rank":")"},{"honor":"1950","rank":")"},{"honor":"1952","rank":")"},{"honor":"1953","rank":")"},{"honor":"1954","rank":")"}]},{"label":"All-League","results":[{"honor":"1948-49","rank":"All-BAA (1st)"},{"honor":"1949-50","rank":"All-NBA (1st)"},{"honor":"1950-51","rank":"All-NBA (1st)"},{"honor":"1951-52","rank":"All-NBA (1st)"},{"honor":"1952-53","rank":"All-NBA (1st)"},{"honor":"1953-54","rank":"All-NBA (1st)"}]},{"label":"Points","results":[{"honor":"1948-49 BAA","rank":"1698 (1st)"},{"honor":"1949-50 NBA","rank":"1865 (1st)"},{"honor":"1950-51 NBA","rank":"1932 (1st)"},{"honor":"1951-52 NBA","rank":"1523 (2nd)"},{"honor":"1952-53 NBA","rank":"1442 (2nd)"},{"honor":"1953-54 NBA","rank":"1306 (4th)"}]},{"label":"Points Per Game","results":[{"honor":"1948-49 BAA","rank":"28.3 (1st)"},{"honor":"1949-50 NBA","rank":"27.4 (1st)"},{"honor":"1950-51 NBA","rank":"28.4 (1st)"},{"honor":"1951-52 NBA","rank":"23.8 (2nd)"},{"honor":"1952-53 NBA","rank":"20.6 (2nd)"},{"honor":"1953-54 NBA","rank":"18.1 (4th)"},{"honor":"Career NBA","rank":"23.1 (25th)"},{"honor":"Career","rank":"23.1 (26th)"}]},{"label":"Total Rebounds","results":[{"honor":"1950-51 NBA","rank":"958 (2nd)"},{"honor":"1951-52 NBA","rank":"866 (3rd)"},{"honor":"1952-53 NBA","rank":"1007 (1st)"},{"honor":"1953-54 NBA","rank":"1028 (2nd)"}]},{"label":"Rebounds Per Game","results":[{"honor":"1950-51 NBA","rank":"14.1 (2nd)"},{"honor":"1951-52 NBA","rank":"13.5 (1st)"},{"honor":"1952-53 NBA","rank":"14.4 (1st)"},{"honor":"1953-54 NBA","rank":"14.3 (2nd)"}]},{"label":"Assists","results":[{"honor":"1948-49 BAA","rank":"218 (7th)"},{"honor":"1950-51 NBA","rank":"208 (15th)"}]},{"label":"Assists Per Game","results":[{"honor":"1948-49 BAA","rank":"3.6 (8th)"},{"honor":"1950-51 NBA","rank":"3.1 (19th)"}]},{"label":"Field Goal Pct","results":[{"honor":"1948-49 BAA","rank":".416 (2nd)"},{"honor":"1949-50 NBA","rank":".407 (5th)"},{"honor":"1950-51 NBA","rank":".428 (3rd)"},{"honor":"1951-52 NBA","rank":".385 (17th)"},{"honor":"1952-53 NBA","rank":".399 (12th)"},{"honor":"1953-54 NBA","rank":".380 (17th)"}]},{"label":"Free Throw Pct","results":[{"honor":"1948-49 BAA","rank":".772 (14th)"},{"honor":"1949-50 NBA","rank":".779 (13th)"},{"honor":"1950-51 NBA","rank":".803 (11th)"},{"honor":"1951-52 NBA","rank":".780 (14th)"},{"honor":"1952-53 NBA","rank":".780 (14th)"},{"honor":"1953-54 NBA","rank":".777 (8th)"}]},{"label":"2-Pt Field Goal Pct","results":[{"honor":"1948-49 BAA","rank":".416 (2nd)"},{"honor":"1949-50 NBA","rank":".407 (5th)"},{"honor":"1950-51 NBA","rank":".428 (3rd)"},{"honor":"1951-52 NBA","rank":".385 (17th)"},{"honor":"1952-53 NBA","rank":".399 (12th)"},{"honor":"1953-54 NBA","rank":".380 (17th)"}]},{"label":"Effective Field Goal Pct","results":[{"honor":"1948-49 BAA","rank":".416 (2nd)"},{"honor":"1949-50 NBA","rank":".407 (5th)"},{"honor":"1950-51 NBA","rank":".428 (3rd)"},{"honor":"1951-52 NBA","rank":".385 (17th)"},{"honor":"1952-53 NBA","rank":".399 (12th)"},{"honor":"1953-54 NBA","rank":".380 (17th)"}]},{"label":"True Shooting Pct","results":[{"honor":"1948-49 BAA","rank":".498 (3rd)"},{"honor":"1949-50 NBA","rank":".487 (4th)"},{"honor":"1950-51 NBA","rank":".509 (5th)"},{"honor":"1951-52 NBA","rank":".459 (18th)"},{"honor":"1952-53 NBA","rank":".480 (12th)"},{"honor":"1953-54 NBA","rank":".466 (14th)"}]},{"label":"Field Goals","results":[{"honor":"1948-49 BAA","rank":"583 (1st)"},{"honor":"1949-50 NBA","rank":"649 (1st)"},{"honor":"1950-51 NBA","rank":"678 (1st)"},{"honor":"1951-52 NBA","rank":"545 (2nd)"},{"honor":"1952-53 NBA","rank":"500 (2nd)"},{"honor":"1953-54 NBA","rank":"441 (4th)"}]},{"label":"Field Goal Attempts","results":[{"honor":"1948-49 BAA","rank":"1403 (2nd)"},{"honor":"1949-50 NBA","rank":"1595 (1st)"},{"honor":"1950-51 NBA","rank":"1584 (1st)"},{"honor":"1951-52 NBA","rank":"1414 (1st)"},{"honor":"1952-53 NBA","rank":"1252 (2nd)"},{"honor":"1953-54 NBA","rank":"1160 (3rd)"}]},{"label":"2-Pt Field Goals","results":[{"honor":"1948-49 BAA","rank":"583 (1st)"},{"honor":"1949-50 NBA","rank":"649 (1st)"},{"honor":"1950-51 NBA","rank":"678 (1st)"},{"honor":"1951-52 NBA","rank":"545 (2nd)"},{"honor":"1952-53 NBA","rank":"500 (2nd)"},{"honor":"1953-54 NBA","rank":"441 (4th)"}]},{"label":"2-Pt Field Goal Attempts","results":[{"honor":"1948-49 BAA","rank":"1403 (2nd)"},{"honor":"1949-50 NBA","rank":"1595 (1st)"},{"honor":"1950-51 NBA","rank":"1584 (1st)"},{"honor":"1951-52 NBA","rank":"1414 (1st)"},{"honor":"1952-53 NBA","rank":"1252 (2nd)"},{"honor":"1953-54 NBA","rank":"1160 (3rd)"}]},{"label":"Field Goals Missed","results":[{"honor":"1948-49 BAA","rank":"820 (2nd)"},{"honor":"1949-50 NBA","rank":"946 (1st)"},{"honor":"1950-51 NBA","rank":"906 (2nd)"},{"honor":"1951-52 NBA","rank":"869 (2nd)"},{"honor":"1952-53 NBA","rank":"752 (2nd)"},{"honor":"1953-54 NBA","rank":"719 (3rd)"}]},{"label":"Free Throws","results":[{"honor":"1948-49 BAA","rank":"532 (1st)"},{"honor":"1949-50 NBA","rank":"567 (1st)"},{"honor":"1950-51 NBA","rank":"576 (1st)"},{"honor":"1951-52 NBA","rank":"433 (3rd)"},{"honor":"1952-53 NBA","rank":"442 (5th)"},{"honor":"1953-54 NBA","rank":"424 (5th)"}]},{"label":"Free Throw Attempts","results":[{"honor":"1948-49 BAA","rank":"689 (1st)"},{"honor":"1949-50 NBA","rank":"728 (1st)"},{"honor":"1950-51 NBA","rank":"717 (1st)"},{"honor":"1951-52 NBA","rank":"555 (3rd)"},{"honor":"1952-53 NBA","rank":"567 (5th)"},{"honor":"1953-54 NBA","rank":"546 (6th)"}]},{"label":"Games","results":[{"honor":"1948-49 BAA","rank":"60 (4th)"},{"honor":"1949-50 NBA","rank":"68 (2nd)"},{"honor":"1950-51 NBA","rank":"68 (3rd)"},{"honor":"1952-53 NBA","rank":"70 (11th)"},{"honor":"1953-54 NBA","rank":"72 (2nd)"}]},{"label":"Minutes Played","results":[{"honor":"1951-52 NBA","rank":"2572 (10th)"},{"honor":"1952-53 NBA","rank":"2651 (10th)"}]},{"label":"Minutes Per Game","results":[{"honor":"1951-52 NBA","rank":"40.2 (6th)"},{"honor":"1952-53 NBA","rank":"37.9 (10th)"}]},{"label":"Personal Fouls","results":[{"honor":"1948-49 BAA","rank":"260 (3rd)"},{"honor":"1949-50 NBA","rank":"297 (1st)"},{"honor":"1950-51 NBA","rank":"308 (1st)"},{"honor":"1951-52 NBA","rank":"286 (1st)"},{"honor":"1952-53 NBA","rank":"290 (4th)"},{"honor":"1953-54 NBA","rank":"268 (6th)"}]},{"label":"Player Efficiency Rating","results":[{"honor":"1951-52 NBA","rank":"26.5 (1st)"},{"honor":"1952-53 NBA","rank":"28.4 (1st)"},{"honor":"1953-54 NBA","rank":"29.0 (1st)"}]},{"label":"Win Shares","results":[{"honor":"1948-49 BAA","rank":"20.9 (1st)"},{"honor":"1949-50 NBA","rank":"21.1 (1st)"},{"honor":"1950-51 NBA","rank":"23.4 (1st)"},{"honor":"1951-52 NBA","rank":"14.4 (2nd)"},{"honor":"1952-53 NBA","rank":"14.6 (2nd)"},{"honor":"1953-54 NBA","rank":"12.7 (4th)"},{"honor":"Career NBA","rank":"108.7 (66th)"},{"honor":"Career","rank":"108.7 (71st)"}]},{"label":"Offensive Win Shares","results":[{"honor":"1948-49 BAA","rank":"17.6 (1st)"},{"honor":"1949-50 NBA","rank":"15.3 (2nd)"},{"honor":"1950-51 NBA","rank":"16.0 (1st)"},{"honor":"1951-52 NBA","rank":"6.4 (7th)"},{"honor":"1952-53 NBA","rank":"7.7 (5th)"},{"honor":"1953-54 NBA","rank":"6.1 (10th)"},{"honor":"Career NBA","rank":"70.0 (56th)"},{"honor":"Career","rank":"70.0 (60th)"}]},{"label":"Defensive Win Shares","results":[{"honor":"1948-49 BAA","rank":"3.2 (5th)"},{"honor":"1949-50 NBA","rank":"5.8 (1st)"},{"honor":"1950-51 NBA","rank":"7.4 (1st)"},{"honor":"1951-52 NBA","rank":"8.0 (1st)"},{"honor":"1952-53 NBA","rank":"6.9 (1st)"},{"honor":"1953-54 NBA","rank":"6.6 (1st)"}]},{"label":"Win Shares Per 48 Minutes","results":[{"honor":"1951-52 NBA","rank":".268 (2nd)"},{"honor":"1952-53 NBA","rank":".264 (1st)"},{"honor":"1953-54 NBA","rank":".258 (3rd)"}]},{"label":"Hall of Fame Probability","results":[{"honor":"99.9%","rank":"99.9%"}]}],"advanced":[{"season":"1948-49","age":24,"team_id":"MNL","lg_id":"BAA","pos":"C","g":60,"mp":0,"per":0,"ts_pct":0.498,"fta_per_fga_pct":0.491,"orb_pct":0,"drb_pct":0,"trb_pct":0,"ast_pct":0,"DUMMY":0,"ows":17.6,"dws":3.2,"ws":20.9,"ws_per_48":0},{"season":"1949-50","age":25,"team_id":"MNL","lg_id":"NBA","pos":"C","g":68,"mp":0,"per":0,"ts_pct":0.487,"fta_per_fga_pct":0.456,"orb_pct":0,"drb_pct":0,"trb_pct":0,"ast_pct":0,"DUMMY":0,"ows":15.3,"dws":5.8,"ws":21.1,"ws_per_48":0},{"season":"1950-51","age":26,"team_id":"MNL","lg_id":"NBA","pos":"C","g":68,"mp":0,"per":0,"ts_pct":0.509,"fta_per_fga_pct":0.453,"orb_pct":0,"drb_pct":0,"trb_pct":0,"ast_pct":0,"DUMMY":0,"ows":16,"dws":7.4,"ws":23.4,"ws_per_48":0},{"season":"1951-52","age":27,"team_id":"MNL","lg_id":"NBA","pos":"C","g":64,"mp":2572,"per":26.5,"ts_pct":0.459,"fta_per_fga_pct":0.393,"orb_pct":0,"drb_pct":0,"trb_pct":0,"ast_pct":0,"DUMMY":0,"ows":6.4,"dws":8,"ws":14.4,"ws_per_48":0.268},{"season":"1952-53","age":28,"team_id":"MNL","lg_id":"NBA","pos":"C","g":70,"mp":2651,"per":28.4,"ts_pct":0.48,"fta_per_fga_pct":0.453,"orb_pct":0,"drb_pct":0,"trb_pct":0,"ast_pct":0,"DUMMY":0,"ows":7.7,"dws":6.9,"ws":14.6,"ws_per_48":0.264},{"season":"1953-54","age":29,"team_id":"MNL","lg_id":"NBA","pos":"C","g":72,"mp":2362,"per":29,"ts_pct":0.466,"fta_per_fga_pct":0.471,"orb_pct":0,"drb_pct":0,"trb_pct":0,"ast_pct":0,"DUMMY":0,"ows":6.1,"dws":6.6,"ws":12.7,"ws_per_48":0.258},{"season":"1955-56","age":31,"team_id":"MNL","lg_id":"NBA","pos":"C","g":37,"mp":765,"per":17.8,"ts_pct":0.455,"fta_per_fga_pct":0.325,"orb_pct":0,"drb_pct":0,"trb_pct":0,"ast_pct":0,"DUMMY":0,"ows":0.8,"dws":0.8,"ws":1.6,"ws_per_48":0.098}]}}