{"name":"Siegfried, Larry","topVideo":"https://youtube.com/watch?v=FAa5g2TPhas","relatedLinks":[{"title":"Larry Siegfried - Wikipedia","url":"https://en.m.wikipedia.org/wiki/Larry_Siegfried"},{"title":"Larry Siegfried Stats | Basketball-Reference.com","url":"https://www.basketball-reference.com/players/s/siegfla01.html"},{"title":"Larry Siegfried | Basketball-Reference.com","url":"https://www.basketball-reference.com/coaches/siegfla01c.html"},{"title":"Stats - Larry Siegfried - NBA.com","url":"https://www.nba.com/stats/player/78147/career"},{"title":"Larry Siegfried, Guard Who Won 5 Titles With Celtics, Is Dead at 71 ...","url":"https://www.nytimes.com/2010/10/16/sports/basketball/16siegfried.html"},{"title":"Larry Siegfried NBA profile and data - Hispanosnba.com","url":"https://en.hispanosnba.com/amp/players/larry-siegfried"},{"title":"NBA Players: Larry Siegfried Profile and Basic Stats","url":"https://www.landofbasketball.com/nba_players/larry_siegfried.htm"},{"title":"Larry Siegfried dies at 71; guard won five NBA titles with the Boston Celtics","url":"https://www.latimes.com/local/obituaries/la-me-1016-larry-siegfried-20101016-story.html?_amp=true"},{"title":"Larry Siegfried - 1964-65 Boston Celtics - 2K Ratings","url":"https://www.2kratings.com/larry-siegfried-1964-65-boston-celtics"},{"title":"Larry Siegfried, who won five NBA titles with the Boston Celtics ... - ESPN","url":"https://www.espn.com/boston/nba/news/story?id=5688671"}],"bio":{"title":"Larry Siegfried","description":"Larry E. Siegfried was an American National Basketball Association player.","url":"https://en.m.wikipedia.org/wiki/Larry_Siegfried","born":"May 22, 1939, Shelby, OH","died":"October 14, 2010, Cleveland, OH","listed_height":"6 ft 3 in (1.91 m)","nba_draft":"1961 / Round: 1 / Pick: 3rd overall","playing_career":"1961–1972","college":"Ohio State (1958–1961)","number":"20","type":"American basketball player","images":[{"url":"https://encrypted-tbn0.gstatic.com/images?q=tbn:ANd9GcSpoYyqS67u7_y31oovPmyi5bZGjMGCa8Skkg&s","source":"https://2kmtcentral.com/18/players/8202/larry-siegfried"},{"url":"https://encrypted-tbn0.gstatic.com/images?q=tbn:ANd9GcQtOcv_aM3vAiWx_PW7QiWVmZSH1Kon0HjxOQ&s","source":"https://2kmtcentral.com/19/players/2093/larry-siegfried"},{"url":"https://encrypted-tbn0.gstatic.com/images?q=tbn:ANd9GcS0Sq3mUbSgjowBPNvr9JANxkoaixPW4fUVgQ&s","source":"https://www.gettyimages.com/photos/boston-celtics-larry-siegfried"},{"url":"https://encrypted-tbn0.gstatic.com/images?q=tbn:ANd9GcTmyTENn7xemgc8AGEapri-lBz8gybxi9yyYw&s","source":"https://ohiobasketballhalloffame.com/hall-of-fame/inductees/2008/larry-siegfried.html"},{"url":"https://encrypted-tbn0.gstatic.com/images?q=tbn:ANd9GcSSIB7GQh1Av01UetOFY-dKkcqjfDfKkGPgvw&s","source":"http://www.boston.com/bostonglobe/obituaries/articles/2010/10/16/larry_siegfried_guard_helped_celtics_win_five_titles/"},{"url":"https://encrypted-tbn0.gstatic.com/images?q=tbn:ANd9GcRzHsThEQd0fZr-J1-wa_sTCFoO9hHyXtkSmw&s","source":"https://2kmtcentral.com/20/players/2093/larry-siegfried"},{"url":"https://encrypted-tbn0.gstatic.com/images?q=tbn:ANd9GcQyA-LnNIIPv_fDfIAQ9LC0R-wbYAeOTJZRjQ&s","source":"https://www.richlandsource.com/sports/turners-vow-rekindles-shelby-legend-larry-siegfried/article_0f7199cc-d0d9-11e5-9e2a-fbaa9d020253.html"},{"url":"https://encrypted-tbn0.gstatic.com/images?q=tbn:ANd9GcT7XEhynzffHvnGVYX0ih4Dn7mQrRnhTOQVEA&s","source":"https://www.thedraftreview.com/index.php?option=com_content&view=article&id=266"}]},"stats":{"honors":[{"label":"Championships","results":[{"honor":"1964","rank":")"},{"honor":"1965","rank":")"},{"honor":"1966","rank":")"},{"honor":"1968","rank":")"},{"honor":"1969","rank":")"}]},{"label":"Amateur Honors","results":[{"honor":"1960-61 NCAA AP All-America (3rd)","rank":"1960-61 NCAA AP All-America (3rd)"}]},{"label":"Assists","results":[{"honor":"1967-68 NBA","rank":"289 (19th)"},{"honor":"1968-69 NBA","rank":"370 (19th)"}]},{"label":"Assists Per Game","results":[{"honor":"1968-69 NBA","rank":"4.7 (17th)"}]},{"label":"Free Throw Pct","results":[{"honor":"1965-66 NBA","rank":".881 (1st)"},{"honor":"1966-67 NBA","rank":".847 (6th)"},{"honor":"1967-68 NBA","rank":".868 (2nd)"},{"honor":"1968-69 NBA","rank":".864 (1st)"},{"honor":"Career NBA","rank":".855 (53rd)"},{"honor":"Career","rank":".855 (57th)"}]},{"label":"True Shooting Pct","results":[{"honor":"1965-66 NBA","rank":".505 (19th)"},{"honor":"1966-67 NBA","rank":".523 (14th)"}]},{"label":"Player Efficiency Rating","results":[{"honor":"1965-66 NBA","rank":"16.5 (18th)"}]},{"label":"Win Shares","results":[{"honor":"1965-66 NBA","rank":"5.8 (19th)"},{"honor":"1966-67 NBA","rank":"6.4 (20th)"}]},{"label":"Defensive Win Shares","results":[{"honor":"1968-69 NBA","rank":"4.4 (10th)"}]},{"label":"Win Shares Per 48 Minutes","results":[{"honor":"1965-66 NBA","rank":".166 (7th)"},{"honor":"1966-67 NBA","rank":".163 (9th)"}]},{"label":"Assist Pct","results":[{"honor":"1966-67 NBA","rank":"17.5 (14th)"},{"honor":"1967-68 NBA","rank":"18.6 (15th)"},{"honor":"1968-69 NBA","rank":"19.3 (16th)"},{"honor":"1969-70 NBA","rank":"19.5 (18th)"},{"honor":"1970-71 NBA","rank":"25.5 (5th)"}]},{"label":"Hall of Fame Probability","results":[{"honor":"1.5%","rank":"1.5%"}]}],"advanced":[{"season":"1963-64","age":24,"team_id":"BOS","lg_id":"NBA","pos":"SG","g":31,"mp":261,"per":11.8,"ts_pct":0.397,"fta_per_fga_pct":0.355,"orb_pct":0,"drb_pct":0,"trb_pct":0,"ast_pct":0,"DUMMY":0,"ows":-0.3,"dws":0.8,"ws":0.5,"ws_per_48":0.084},{"season":"1964-65","age":25,"team_id":"BOS","lg_id":"NBA","pos":"SG","g":72,"mp":996,"per":14,"ts_pct":0.475,"fta_per_fga_pct":0.336,"orb_pct":0,"drb_pct":0,"trb_pct":0,"ast_pct":15.9,"DUMMY":0,"ows":1,"dws":2.1,"ws":3.2,"ws_per_48":0.152},{"season":"1965-66","age":26,"team_id":"BOS","lg_id":"NBA","pos":"PG","g":71,"mp":1675,"per":16.5,"ts_pct":0.505,"fta_per_fga_pct":0.377,"orb_pct":0,"drb_pct":0,"trb_pct":0,"ast_pct":14.1,"DUMMY":0,"ows":3.1,"dws":2.7,"ws":5.8,"ws_per_48":0.166},{"season":"1966-67","age":27,"team_id":"BOS","lg_id":"NBA","pos":"PG","g":73,"mp":1891,"per":16.2,"ts_pct":0.522,"fta_per_fga_pct":0.417,"orb_pct":0,"drb_pct":0,"trb_pct":0,"ast_pct":17.5,"DUMMY":0,"ows":3.7,"dws":2.7,"ws":6.4,"ws_per_48":0.163},{"season":"1967-68","age":28,"team_id":"BOS","lg_id":"NBA","pos":"PG","g":62,"mp":1937,"per":13.1,"ts_pct":0.506,"fta_per_fga_pct":0.432,"orb_pct":0,"drb_pct":0,"trb_pct":0,"ast_pct":18.6,"DUMMY":0,"ows":2.2,"dws":2.9,"ws":5.1,"ws_per_48":0.126},{"season":"1968-69","age":29,"team_id":"BOS","lg_id":"NBA","pos":"PG","g":79,"mp":2560,"per":13.6,"ts_pct":0.466,"fta_per_fga_pct":0.377,"orb_pct":0,"drb_pct":0,"trb_pct":0,"ast_pct":19.3,"DUMMY":0,"ows":1.2,"dws":4.4,"ws":5.6,"ws_per_48":0.106},{"season":"1969-70","age":30,"team_id":"BOS","lg_id":"NBA","pos":"PG","g":78,"mp":2081,"per":13.7,"ts_pct":0.485,"fta_per_fga_pct":0.285,"orb_pct":0,"drb_pct":0,"trb_pct":0,"ast_pct":19.5,"DUMMY":0,"ows":0.9,"dws":2,"ws":2.9,"ws_per_48":0.067},{"season":"1970-71","age":31,"team_id":"SDR","lg_id":"NBA","pos":"PG","g":53,"mp":1673,"per":11.6,"ts_pct":0.474,"fta_per_fga_pct":0.405,"orb_pct":0,"drb_pct":0,"trb_pct":5.4,"ast_pct":25.5,"DUMMY":0,"ows":0.6,"dws":2.9,"ws":3.5,"ws_per_48":0.101},{"season":"1971-72","age":32,"team_id":"TOT","lg_id":"NBA","pos":"PG","g":31,"mp":558,"per":6.9,"ts_pct":0.424,"fta_per_fga_pct":0.301,"orb_pct":0,"drb_pct":0,"trb_pct":3.6,"ast_pct":15.9,"DUMMY":0,"ows":-0.3,"dws":0.4,"ws":0.1,"ws_per_48":0.01},{"season":"1971-72","age":32,"team_id":"HOU","lg_id":"NBA","pos":"PG","g":10,"mp":223,"per":6,"ts_pct":0.46,"fta_per_fga_pct":0.304,"orb_pct":0,"drb_pct":0,"trb_pct":2,"ast_pct":10.8,"DUMMY":0,"ows":0,"dws":0.2,"ws":0.2,"ws_per_48":0.044},{"season":"1971-72","age":32,"team_id":"ATL","lg_id":"NBA","pos":"PG","g":21,"mp":335,"per":7.6,"ts_pct":0.402,"fta_per_fga_pct":0.299,"orb_pct":0,"drb_pct":0,"trb_pct":4.7,"ast_pct":19.2,"DUMMY":0,"ows":-0.3,"dws":0.2,"ws":-0.1,"ws_per_48":-0.012}]}}